mistocr/__init__.py
mistocr/_modidx.py
mistocr/core.py
mistocr/pipeline.py
mistocr/refine.py
mistocr-0.4.1.dist-info/licenses/LICENSE
mistocr-0.4.1.dist-info/METADATA
mistocr-0.4.1.dist-info/WHEEL
mistocr-0.4.1.dist-info/entry_points.txt
mistocr-0.4.1.dist-info/top_level.txt
mistocr-0.4.1.dist-info/RECORD
